docstrfmt/__init__.py
docstrfmt/__main__.py
docstrfmt/const.py
docstrfmt/debug.py
docstrfmt/docstrfmt.py
docstrfmt/exceptions.py
docstrfmt/main.py
docstrfmt/rst_extras.py
docstrfmt/server.py
docstrfmt/util.py
docstrfmt-2.0.1.dist-info/entry_points.txt
docstrfmt-2.0.1.dist-info/licenses/LICENSE.txt
docstrfmt-2.0.1.dist-info/WHEEL
docstrfmt-2.0.1.dist-info/METADATA
docstrfmt-2.0.1.dist-info/RECORD
