Metadata-Version: 2.4
Name: docstrfmt
Version: 2.0.1
Summary: docstrfmt: A formatter for Sphinx flavored reStructuredText.
Keywords: black,docutils,autoformatter,formatter,lint,restructuredtext,rst,sphinx
Author-email: Joel Payne <lilspazjoekp@gmail.com>
Maintainer-email: Joel Payne <lilspazjoekp@gmail.com>
Requires-Python: >=3.10
Classifier: Development Status :: 4 - Beta
Classifier: Environment :: Console
Classifier: Intended Audience :: Developers
Classifier: License :: OSI Approved :: MIT License
Classifier: Programming Language :: Python :: 3
Classifier: Programming Language :: Python :: 3.10
Classifier: Programming Language :: Python :: 3.11
Classifier: Programming Language :: Python :: 3.12
Classifier: Programming Language :: Python :: 3.13
Classifier: Programming Language :: Python :: 3.14
Classifier: Programming Language :: Python
Classifier: Topic :: Documentation
Classifier: Topic :: Documentation :: Sphinx
Classifier: Topic :: Software Development :: Documentation
Classifier: Topic :: Utilities
License-File: LICENSE.txt
Requires-Dist: black>=24
Requires-Dist: click>=8
Requires-Dist: coverage>=7.11.0
Requires-Dist: docutils>=0.21
Requires-Dist: docutils-stubs==0.0.22
Requires-Dist: libcst>=1
Requires-Dist: platformdirs>=4
Requires-Dist: roman
Requires-Dist: sphinx>=7
Requires-Dist: tabulate>=0.9
Requires-Dist: tomli>=0.10;python_version<'3.11'
Requires-Dist: types-docutils==0.22.3.20251115
Requires-Dist: aiohttp ; extra == "d"
Project-URL: Issue Tracker, https://github.com/LilSpazJoekp/docstrfmt/issues
Project-URL: Source Code, https://github.com/LilSpazJoekp/docstrfmt
Provides-Extra: d
